fake_traffic/__init__.py
fake_traffic/cli.py
fake_traffic/fake_traffic.py
fake_traffic/version.py
fake_traffic-3.2.dist-info/LICENSE
fake_traffic-3.2.dist-info/METADATA
fake_traffic-3.2.dist-info/WHEEL
fake_traffic-3.2.dist-info/entry_points.txt
fake_traffic-3.2.dist-info/top_level.txt
fake_traffic-3.2.dist-info/RECORD
